kpet/__main__.py
kpet/config.py
kpet/http.py
kpet/log.py
kpet/version.py
kpet/cli/ctx.py
kpet/cli/get.py
kpet/cli/main.py
kpet/cli/show.py
tests/test_version.py
kpet-0.0.2.dist-info/LICENSE
kpet-0.0.2.dist-info/METADATA
kpet-0.0.2.dist-info/WHEEL
kpet-0.0.2.dist-info/entry_points.txt
kpet-0.0.2.dist-info/top_level.txt
kpet-0.0.2.dist-info/RECORD
