Metadata-Version: 2.1
Name: kpet
Version: 0.0.2
Summary: Command line tool to explore the Kubernetes API using Python expressions
Home-page: https://github.com/joaompinto/kpet
Author: João Pinto
Author-email: lamego.pinto@gmail.com
License: MIT
Platform: UNKNOWN
License-File: LICENSE
Requires-Dist: dinterpol
Requires-Dist: httpx
Requires-Dist: metadict
Requires-Dist: rich
Requires-Dist: pyyaml
Requires-Dist: typer
